<Configuration ID="c0d68b43-5bd7-43a6-846f-fbcc77efcfd3">
  <Add OfficeClientEdition="64" Channel="Current">
    <Product ID="O365ProPlusRetail">
      <Language ID="pt-br" />
      <ExcludeApp ID="Groove" />
      <ExcludeApp ID="Lync" />
      <ExcludeApp ID="OneDrive" />
      <ExcludeApp ID="OneNote" />
      <ExcludeApp ID="OutlookForWindows" />
      <ExcludeApp ID="Publisher" />
      <ExcludeApp ID="Teams" />
      <ExcludeApp ID="Bing" />
    </Product>
  </Add>
  <Updates Enabled="TRUE" />
  <RemoveMSI />
  <Display Level="None" AcceptEULA="TRUE" />
</Configuration>